LICENSE
MANIFEST.in
README.md
pyproject.toml
setup.cfg
setup.py
pretix_sumup/__init__.py
pretix_sumup/apps.py
pretix_sumup/payment.py
pretix_sumup/signals.py
pretix_sumup.egg-info/PKG-INFO
pretix_sumup.egg-info/SOURCES.txt
pretix_sumup.egg-info/dependency_links.txt
pretix_sumup.egg-info/entry_points.txt
pretix_sumup.egg-info/top_level.txt
pretix_sumup/locale/django.pot
pretix_sumup/locale/de/LC_MESSAGES/django.po
pretix_sumup/locale/de_Informal/.gitkeep
pretix_sumup/locale/de_Informal/LC_MESSAGES/django.po
pretix_sumup/locale/es/LC_MESSAGES/django.po
pretix_sumup/locale/fr/LC_MESSAGES/django.po
pretix_sumup/locale/it/LC_MESSAGES/django.po
pretix_sumup/static/pretix_sumup/.gitkeep
pretix_sumup/static/pretix_sumup/sumup-logo-black.svg
pretix_sumup/templates/pretix_sumup/.gitkeep
pretix_sumup/templates/pretix_sumup/checkout_confirm_render.html
pretix_sumup/templates/pretix_sumup/checkout_payment_form.html
pretix_sumup/templates/pretix_sumup/control.html
pretix_sumup/templates/pretix_sumup/not_available.html
pretix_sumup/templates/pretix_sumup/pending.html
pretix_sumup/templates/pretix_sumup/prepare.html
pretix_sumup/templates/pretix_sumup/email/order_pending.txt
tests/test_main.py