Metadata-Version: 2.1
Name: pretix-sumup
Version: 1.0.2
Summary: Sumup plugin
Author-email: Ronan Le Meillat <ronan@highcanfly.club>
Maintainer-email: Ronan Le Meillat <ronan@highcanfly.club>
License: GNU AFFERO GENERAL PUBLIC LICENSE
Project-URL: homepage, https://github.com/highcanfly/pretix-sumup
Project-URL: repository, https://github.com/highcanfly/pretix-sumup
Keywords: pretix
License-File: LICENSE
